{"owner_id":"976110","members":{"1563594":{"local_score":46,"global_score":0,"name":"marcoparadina","id":"1563594","stars":11,"completion_day_level":{"2":{"2":{"get_star_ts":1638441702},"1":{"get_star_ts":1638441213}},"4":{"1":{"get_star_ts":1638650496}},"1":{"2":{"get_star_ts":1638397885},"1":{"get_star_ts":1638364361}},"9":{"1":{"get_star_ts":1639050992}},"3":{"1":{"get_star_ts":1638517809},"2":{"get_star_ts":1638522211}},"6":{"1":{"get_star_ts":1638816260}},"7":{"1":{"get_star_ts":1638868553},"2":{"get_star_ts":1638868895}}},"last_star_ts":1639050992},"1426905":{"last_star_ts":1639508002,"completion_day_level":{"10":{"2":{"get_star_ts":1639134456},"1":{"get_star_ts":1639133663}},"13":{"1":{"get_star_ts":1639387241},"2":{"get_star_ts":1639387788}},"1":{"1":{"get_star_ts":1638351169},"2":{"get_star_ts":1638351379}},"9":{"2":{"get_star_ts":1639043927},"1":{"get_star_ts":1639038878}},"3":{"2":{"get_star_ts":1638526943},"1":{"get_star_ts":1638524661}},"7":{"1":{"get_star_ts":1638868874},"2":{"get_star_ts":1638869645}},"5":{"2":{"get_star_ts":1638725899},"1":{"get_star_ts":1638723369}},"11":{"1":{"get_star_ts":1639230437},"2":{"get_star_ts":1639230901}},"2":{"2":{"get_star_ts":1638436202},"1":{"get_star_ts":1638435951}},"14":{"2":{"get_star_ts":1639508002},"1":{"get_star_ts":1639473333}},"4":{"2":{"get_star_ts":1638596687},"1":{"get_star_ts":1638595998}},"8":{"1":{"get_star_ts":1638947832},"2":{"get_star_ts":1638993347}},"12":{"1":{"get_star_ts":1639332288},"2":{"get_star_ts":1639334008}},"6":{"1":{"get_star_ts":1638808019},"2":{"get_star_ts":1638809164}}},"stars":28,"local_score":175,"global_score":0,"id":"1426905","name":"Davide Palmiotti"},"976359":{"last_star_ts":1639573370,"local_score":248,"global_score":0,"id":"976359","name":"riccardo-negri","stars":30,"completion_day_level":{"11":{"2":{"get_star_ts":1639200435},"1":{"get_star_ts":1639200185}},"2":{"1":{"get_star_ts":1638421397},"2":{"get_star_ts":1638421546}},"4":{"1":{"get_star_ts":1638596634},"2":{"get_star_ts":1638596989}},"14":{"1":{"get_star_ts":1639472945},"2":{"get_star_ts":1639480883}},"8":{"2":{"get_star_ts":1638980683},"1":{"get_star_ts":1638980296}},"12":{"1":{"get_star_ts":1639288799},"2":{"get_star_ts":1639301636}},"6":{"1":{"get_star_ts":1638767924},"2":{"get_star_ts":1638770783}},"15":{"1":{"get_star_ts":1639571648},"2":{"get_star_ts":1639573370}},"13":{"2":{"get_star_ts":1639385465},"1":{"get_star_ts":1639384867}},"10":{"1":{"get_star_ts":1639114116},"2":{"get_star_ts":1639114972}},"1":{"2":{"get_star_ts":1638358027},"1":{"get_star_ts":1638355948}},"9":{"2":{"get_star_ts":1639052740},"1":{"get_star_ts":1639042196}},"3":{"1":{"get_star_ts":1638508800},"2":{"get_star_ts":1638511706}},"5":{"2":{"get_star_ts":1638682308},"1":{"get_star_ts":1638681478}},"7":{"1":{"get_star_ts":1638854287},"2":{"get_star_ts":1638855274}}}},"1009246":{"name":"Tommimon","local_score":286,"global_score":0,"id":"1009246","completion_day_level":{"1":{"1":{"get_star_ts":1638334959},"2":{"get_star_ts":1638335128}},"13":{"1":{"get_star_ts":1639373334},"2":{"get_star_ts":1639374064}},"10":{"1":{"get_star_ts":1639113318},"2":{"get_star_ts":1639114051}},"7":{"2":{"get_star_ts":1638854378},"1":{"get_star_ts":1638853980}},"5":{"1":{"get_star_ts":1638682963},"2":{"get_star_ts":1638685626}},"3":{"1":{"get_star_ts":1638508548},"2":{"get_star_ts":1638510303}},"9":{"1":{"get_star_ts":1639026643},"2":{"get_star_ts":1639028091}},"8":{"2":{"get_star_ts":1638948922},"1":{"get_star_ts":1638941068}},"14":{"1":{"get_star_ts":1639475777},"2":{"get_star_ts":1639478842}},"4":{"1":{"get_star_ts":1638596790},"2":{"get_star_ts":1638597589}},"2":{"2":{"get_star_ts":1638421633},"1":{"get_star_ts":1638421498}},"11":{"2":{"get_star_ts":1639200971},"1":{"get_star_ts":1639200680}},"15":{"2":{"get_star_ts":1639552439},"1":{"get_star_ts":1639548097}},"6":{"1":{"get_star_ts":1638767371},"2":{"get_star_ts":1638769029}},"12":{"1":{"get_star_ts":1639286217},"2":{"get_star_ts":1639286840}}},"stars":30,"last_star_ts":1639552439},"976110":{"global_score":0,"local_score":201,"name":"Matteo Negro","id":"976110","completion_day_level":{"7":{"2":{"get_star_ts":1638869124},"1":{"get_star_ts":1638868720}},"5":{"1":{"get_star_ts":1638692556},"2":{"get_star_ts":1638700551}},"3":{"2":{"get_star_ts":1638525097},"1":{"get_star_ts":1638517764}},"9":{"1":{"get_star_ts":1639039690},"2":{"get_star_ts":1639073863}},"1":{"1":{"get_star_ts":1638349931},"2":{"get_star_ts":1638357165}},"13":{"2":{"get_star_ts":1639386515},"1":{"get_star_ts":1639378274}},"10":{"1":{"get_star_ts":1639121540},"2":{"get_star_ts":1639124017}},"6":{"1":{"get_star_ts":1638778059},"2":{"get_star_ts":1638792025}},"12":{"1":{"get_star_ts":1639307214},"2":{"get_star_ts":1639311253}},"8":{"1":{"get_star_ts":1638948023},"2":{"get_star_ts":1638976243}},"4":{"2":{"get_star_ts":1638612283},"1":{"get_star_ts":1638610918}},"14":{"1":{"get_star_ts":1639473781},"2":{"get_star_ts":1639516243}},"11":{"1":{"get_star_ts":1639204353},"2":{"get_star_ts":1639204841}},"2":{"1":{"get_star_ts":1638431284},"2":{"get_star_ts":1638432062}}},"stars":28,"last_star_ts":1639516243},"1602587":{"local_score":96,"global_score":0,"id":"1602587","name":"john-galt-10","stars":22,"completion_day_level":{"9":{"1":{"get_star_ts":1639055763},"2":{"get_star_ts":1639083348}},"3":{"2":{"get_star_ts":1638543386},"1":{"get_star_ts":1638524393}},"7":{"1":{"get_star_ts":1638868161},"2":{"get_star_ts":1638872286}},"5":{"2":{"get_star_ts":1638701520},"1":{"get_star_ts":1638698754}},"10":{"1":{"get_star_ts":1639125664},"2":{"get_star_ts":1639126948}},"1":{"2":{"get_star_ts":1638365495},"1":{"get_star_ts":1638354681}},"6":{"2":{"get_star_ts":1638822997},"1":{"get_star_ts":1638819237}},"11":{"2":{"get_star_ts":1639245831},"1":{"get_star_ts":1639245404}},"2":{"1":{"get_star_ts":1638446154},"2":{"get_star_ts":1638446518}},"4":{"1":{"get_star_ts":1638630557},"2":{"get_star_ts":1638635793}},"8":{"1":{"get_star_ts":1638962020},"2":{"get_star_ts":1638981393}}},"last_star_ts":1639245831},"1007452":{"stars":30,"completion_day_level":{"7":{"1":{"get_star_ts":1638862744},"2":{"get_star_ts":1638863494}},"5":{"2":{"get_star_ts":1638718242},"1":{"get_star_ts":1638693187}},"3":{"1":{"get_star_ts":1638513169},"2":{"get_star_ts":1638520253}},"9":{"2":{"get_star_ts":1639050473},"1":{"get_star_ts":1639047693}},"1":{"1":{"get_star_ts":1638345949},"2":{"get_star_ts":1638348710}},"10":{"2":{"get_star_ts":1639125881},"1":{"get_star_ts":1639123172}},"13":{"2":{"get_star_ts":1639383476},"1":{"get_star_ts":1639382750}},"15":{"2":{"get_star_ts":1639565488},"1":{"get_star_ts":1639562993}},"6":{"2":{"get_star_ts":1638777996},"1":{"get_star_ts":1638777778}},"12":{"1":{"get_star_ts":1639348543},"2":{"get_star_ts":1639388297}},"8":{"2":{"get_star_ts":1638972020},"1":{"get_star_ts":1638953130}},"4":{"1":{"get_star_ts":1638631194},"2":{"get_star_ts":1638632041}},"14":{"2":{"get_star_ts":1639482364},"1":{"get_star_ts":1639472897}},"2":{"1":{"get_star_ts":1638432027},"2":{"get_star_ts":1638432634}},"11":{"2":{"get_star_ts":1639213959},"1":{"get_star_ts":1639213589}}},"local_score":224,"global_score":0,"id":"1007452","name":"Gonduls","last_star_ts":1639565488},"1589938":{"local_score":7,"id":"1589938","global_score":0,"name":"alexeats","stars":5,"completion_day_level":{"2":{"1":{"get_star_ts":1638445105},"2":{"get_star_ts":1638451566}},"1":{"2":{"get_star_ts":1638373504},"1":{"get_star_ts":1638365653}},"3":{"1":{"get_star_ts":1638525970}}},"last_star_ts":1638525970},"445094":{"stars":9,"completion_day_level":{"2":{"1":{"get_star_ts":1638436873},"2":{"get_star_ts":1638437033}},"1":{"2":{"get_star_ts":1638355636},"1":{"get_star_ts":1638355187}},"4":{"2":{"get_star_ts":1638799215},"1":{"get_star_ts":1638783096}},"3":{"2":{"get_star_ts":1638524307},"1":{"get_star_ts":1638523397}},"5":{"1":{"get_star_ts":1638869480}}},"global_score":0,"local_score":36,"name":"Alessandro Nazzari","id":"445094","last_star_ts":1638869480},"564880":{"global_score":0,"local_score":131,"name":"Marco Molè","id":"564880","stars":26,"completion_day_level":{"12":{"2":{"get_star_ts":1639345408},"1":{"get_star_ts":1639342272}},"6":{"2":{"get_star_ts":1638811654},"1":{"get_star_ts":1638810133}},"11":{"2":{"get_star_ts":1639237334},"1":{"get_star_ts":1639236670}},"2":{"2":{"get_star_ts":1638437828},"1":{"get_star_ts":1638436866}},"4":{"2":{"get_star_ts":1638659117},"1":{"get_star_ts":1638656797}},"8":{"2":{"get_star_ts":1639000703},"1":{"get_star_ts":1638975138}},"9":{"2":{"get_star_ts":1639062533},"1":{"get_star_ts":1639041394}},"3":{"2":{"get_star_ts":1638521752},"1":{"get_star_ts":1638519400}},"5":{"2":{"get_star_ts":1638732047},"1":{"get_star_ts":1638728842}},"7":{"2":{"get_star_ts":1638869384},"1":{"get_star_ts":1638868974}},"10":{"2":{"get_star_ts":1639131007},"1":{"get_star_ts":1639129823}},"13":{"1":{"get_star_ts":1639395455},"2":{"get_star_ts":1639395465}},"1":{"1":{"get_star_ts":1638351598},"2":{"get_star_ts":1638353185}}},"last_star_ts":1639395465}},"last_modified":1639575393,"event":"2021"}